{"file":"mcYao_tex.png","res":{"annui_yao_5":{"x":303,"y":153,"w":143,"h":145},"annui_yao_9":{"x":759,"y":1,"w":148,"h":150},"annui_yao_14":{"x":1,"y":1,"w":150,"h":150},"annui_yao_1":{"x":443,"y":737,"w":143,"h":143},"annui_yao_17":{"x":1,"y":153,"w":150,"h":150},"annui_yao_12":{"x":1,"y":305,"w":150,"h":150},"annui_yao_13":{"x":1,"y":457,"w":150,"h":150},"annui_yao_20":{"x":153,"y":153,"w":148,"h":150},"annui_yao_10":{"x":1,"y":609,"w":150,"h":150},"annui_yao_15":{"x":1,"y":761,"w":150,"h":150},"annui_yao_22":{"x":153,"y":761,"w":143,"h":148},"annui_yao_21":{"x":153,"y":305,"w":148,"h":150},"annui_yao_7":{"x":609,"y":1,"w":148,"h":150},"annui_yao_16":{"x":153,"y":1,"w":150,"h":150},"annui_yao_18":{"x":305,"y":1,"w":150,"h":150},"annui_yao_2":{"x":733,"y":153,"w":143,"h":143},"annui_yao_23":{"x":303,"y":300,"w":143,"h":145},"annui_yao_4":{"x":588,"y":737,"w":143,"h":143},"annui_yao_11":{"x":457,"y":1,"w":150,"h":150},"annui_yao_3":{"x":303,"y":447,"w":143,"h":143},"annui_yao_0":{"x":303,"y":592,"w":143,"h":143},"annui_yao_19":{"x":153,"y":457,"w":148,"h":150},"annui_yao_8":{"x":153,"y":609,"w":148,"h":150},"annui_yao_6":{"x":298,"y":761,"w":143,"h":148}},"mc":{"mcYao":{"labels":[{"end":24,"frame":1,"name":"annui_yao"}],"frameRate":24,"frames":[{"duration":1,"y":-72,"res":"annui_yao_0","x":-72},{"duration":1,"y":-72,"res":"annui_yao_1","x":-72},{"duration":1,"y":-72,"res":"annui_yao_2","x":-72},{"duration":1,"y":-72,"res":"annui_yao_3","x":-72},{"duration":1,"y":-72,"res":"annui_yao_4","x":-72},{"duration":1,"y":-72,"res":"annui_yao_5","x":-72},{"duration":1,"y":-74,"res":"annui_yao_6","x":-72},{"duration":1,"y":-75,"res":"annui_yao_7","x":-74},{"duration":1,"y":-75,"res":"annui_yao_8","x":-74},{"duration":1,"y":-75,"res":"annui_yao_9","x":-74},{"duration":1,"y":-75,"res":"annui_yao_10","x":-75},{"duration":1,"y":-75,"res":"annui_yao_11","x":-75},{"duration":1,"y":-75,"res":"annui_yao_12","x":-75},{"duration":1,"y":-75,"res":"annui_yao_13","x":-75},{"duration":1,"y":-75,"res":"annui_yao_14","x":-75},{"duration":1,"y":-75,"res":"annui_yao_15","x":-75},{"duration":1,"y":-75,"res":"annui_yao_16","x":-75},{"duration":1,"y":-75,"res":"annui_yao_17","x":-75},{"duration":1,"y":-75,"res":"annui_yao_18","x":-75},{"duration":1,"y":-75,"res":"annui_yao_19","x":-74},{"duration":1,"y":-75,"res":"annui_yao_20","x":-74},{"duration":1,"y":-75,"res":"annui_yao_21","x":-74},{"duration":1,"y":-74,"res":"annui_yao_22","x":-72},{"duration":1,"y":-72,"res":"annui_yao_23","x":-72}],"events":[]}}}